mx_bluesky/Getting started.ipynb
mx_bluesky/__init__.py
mx_bluesky/__main__.py
mx_bluesky/_version.py
mx_bluesky/definitions.py
mx_bluesky/jupyter_example.ipynb
mx_bluesky/beamlines/__init__.py
mx_bluesky/beamlines/aithre_lasershaping/__init__.py
mx_bluesky/beamlines/aithre_lasershaping/beamline_safe.py
mx_bluesky/beamlines/aithre_lasershaping/check_goniometer_performance.py
mx_bluesky/beamlines/aithre_lasershaping/goniometer_controls.py
mx_bluesky/beamlines/aithre_lasershaping/pin_tip_centring.py
mx_bluesky/beamlines/aithre_lasershaping/robot_load.py
mx_bluesky/beamlines/aithre_lasershaping/experiment_plans/__init__.py
mx_bluesky/beamlines/aithre_lasershaping/experiment_plans/robot_load_plan.py
mx_bluesky/beamlines/aithre_lasershaping/parameters/__init__.py
mx_bluesky/beamlines/aithre_lasershaping/parameters/constants.py
mx_bluesky/beamlines/aithre_lasershaping/parameters/robot_load_parameters.py
mx_bluesky/beamlines/i02_1/parameters/__init__.py
mx_bluesky/beamlines/i02_1/parameters/gridscan.py
mx_bluesky/beamlines/i04/__init__.py
mx_bluesky/beamlines/i04/redis_to_murko_forwarder.py
mx_bluesky/beamlines/i04/thawing_plan.py
mx_bluesky/beamlines/i04/callbacks/__init__.py
mx_bluesky/beamlines/i04/callbacks/murko_callback.py
mx_bluesky/beamlines/i04/experiment_plans/__init__.py
mx_bluesky/beamlines/i04/experiment_plans/i04_grid_detect_then_xray_centre_plan.py
mx_bluesky/beamlines/i04/external_interaction/__init__.py
mx_bluesky/beamlines/i04/external_interaction/config_server.py
mx_bluesky/beamlines/i04/oav_centering_plans/__init__.py
mx_bluesky/beamlines/i04/oav_centering_plans/oav_imaging.py
mx_bluesky/beamlines/i04/parameters/__init__.py
mx_bluesky/beamlines/i04/parameters/constants.py
mx_bluesky/beamlines/i23/__init__.py
mx_bluesky/beamlines/i23/serial.py
mx_bluesky/beamlines/i24/__init__.py
mx_bluesky/beamlines/i24/jungfrau_commissioning/__init__.py
mx_bluesky/beamlines/i24/jungfrau_commissioning/composites.py
mx_bluesky-1.5.16.dist-info/licenses/LICENSE
mx_bluesky-1.5.16.dist-info/METADATA
mx_bluesky-1.5.16.dist-info/WHEEL
mx_bluesky-1.5.16.dist-info/entry_points.txt
mx_bluesky-1.5.16.dist-info/top_level.txt
mx_bluesky-1.5.16.dist-info/RECORD
