Metadata-Version: 2.4
Name: mx-bluesky
Version: 1.5.16
Summary: Bluesky tools for MX Beamlines at DLS
Author-email: Dominic Oram <dominic.oram@diamond.ac.uk>
License:                                  Apache License
Project-URL: GitHub, https://github.com/DiamondLightSource/mx-bluesky
Classifier: Development Status :: 3 - Alpha
Classifier: License :: OSI Approved :: Apache Software License
Classifier: Programming Language :: Python :: 3.11
Classifier: Programming Language :: Python :: 3.12
Classifier: Programming Language :: Python :: 3.13
Requires-Python: >=3.11
License-File: LICENSE
Requires-Dist: annotated_types
Requires-Dist: caproto
Requires-Dist: fastapi[all]
Requires-Dist: flask-restful
Requires-Dist: jupyterlab
Requires-Dist: matplotlib
Requires-Dist: nexgen>=0.11.0
Requires-Dist: numpy>=2.3.5
Requires-Dist: opencv-python
Requires-Dist: opentelemetry-distro
Requires-Dist: opentelemetry-exporter-otlp
Requires-Dist: pydantic
Requires-Dist: pydantic-extra-types>=2.10.1
Requires-Dist: pyepics
Requires-Dist: pyzmq
Requires-Dist: requests
Requires-Dist: scanspec
Requires-Dist: scipy
Requires-Dist: semver
Requires-Dist: deepdiff
Requires-Dist: matplotlib
Requires-Dist: cachetools
Requires-Dist: bluesky-stomp>=0.2.0
Requires-Dist: daq-config-server>=v1.0.0-rc.2
Requires-Dist: blueapi>=1.8.0
Requires-Dist: ophyd>=1.10.5
Requires-Dist: ophyd-async>=0.14.0
Requires-Dist: bluesky>=1.14.6
Requires-Dist: dls-dodal==1.69.0
Dynamic: license-file
